{
  "tableConfig": {
    "name": "project-big-wbs",
    "maxHeight": "500",
    "highlightCurrentRow": true,
    "isTableData": true,
    "emptyText": "",
    "inputConfig": {
      "props": [
        "jobDescription",
        "dutyPersonName",
        "supportPersonName",
        "planStartDate",
        "planEndDate",
        "weight",
        "index"
      ]
    },
    "columns": [{
        "label": "序号",
        "align": "center",
        "prop": "index",
        "minWidth": 50
      },
      {
        "label": "任务名称",
        "prop": "jobDescription",
        "align": "left",
        "minWidth": 245
      },
      {
        "label": "分项责任人",
        "prop": "dutyPersonName",
        "align": "left",
        "width": 120,
        "form": {
          "type": "select"
        }
      },
      {
        "label": "责任部门",
        "align": "left",
        "prop": "dutyDept",
        "minWidth": 200
      },
      {
        "label": "支撑人",
        "align": "left",
        "prop": "supportPersonName",
        "minWwidth": 120,
        "form": {
          "type": "select"
        }
      },
      {
        "label": "计划开始时间",
        "align": "left",
        "prop": "planStartDate",
        "width": 100,
        "form": {
          "type": "date-picker"
        }
      },
      {
        "label": "预计完成时间",
        "align": "left",
        "prop": "planEndDate",
        "width": 100,
        "form": {
          "type": "date-picker"
        }
      },
      {
        "label": "实际完成时间",
        "align": "left",
        "prop": "actualEndDate",
        "width": 100,
        "form": {
          "type": "date-picker"
        }
      },
      {
        "label": "偏差天数",
        "align": "left",
        "prop": "deviationDay",
        "width": 80,
        "valFn": "deviation"
      },
      {
        "label": "计划状态",
        "align": "left",
        "prop": "planStatus_ZH",
        "minWidth": 80
      },
      {
        "label": "权重(%)",
        "align": "left",
        "prop": "weight",
        "minWidth": 70
      },
      {
        "label": "操作",
        "align": "center",
        "type": "action-icons",
        "width": 100,
        "icons": [{
            "name": "assignment",
            "title": "任务分派",
            "text": "分派"
          },
          {
            "name": "remove",
            "title": "删除",
            "className": "text-danger",
            "text": "删除"
          }
        ]
      }
    ]
  }
}